{
  "main": {
    "id": "90558f413090c4f7",
    "type": "split",
    "children": [
      {
        "id": "bcf03437569e492f",
        "type": "tabs",
        "children": [
          {
            "id": "4bf4853a49b1a8ba",
            "type": "leaf",
            "state": {
              "type": "markdown",
              "state": {
                "file": "DP Questions.md",
                "mode": "source",
                "source": true
              },
              "icon": "lucide-file",
              "title": "DP Questions"
            }
          },
          {
            "id": "ad45449687321a1d",
            "type": "leaf",
            "state": {
              "type": "markdown",
              "state": {
                "file": "DP Questions.md",
                "mode": "source",
                "source": false
              },
              "icon": "lucide-file",
              "title": "DP Questions"
            }
          },
          {
            "id": "677eb730afe31aec",
            "type": "leaf",
            "state": {
              "type": "markdown",
              "state": {
                "file": "🍕 Food Delivery App — Schema Design.md",
                "mode": "source",
                "source": false
              },
              "icon": "lucide-file",
              "title": "🍕 Food Delivery App — Schema Design"
            }
          },
          {
            "id": "76208cb8598e16bd",
            "type": "leaf",
            "state": {
              "type": "markdown",
              "state": {
                "file": "🍕 Food Delivery App — Schema Design.md",
                "mode": "source",
                "source": false
              },
              "icon": "lucide-file",
              "title": "🍕 Food Delivery App — Schema Design"
            }
          }
        ],
        "currentTab": 3
      }
    ],
    "direction": "vertical"
  },
  "left": {
    "id": "16bbd574481cb271",
    "type": "split",
    "children": [
      {
        "id": "c0aca3633803d940",
        "type": "tabs",
        "children": [
          {
            "id": "2f9ce7eebe2e0830",
            "type": "leaf",
            "state": {
              "type": "file-explorer",
              "state": {
                "sortOrder": "alphabetical",
                "autoReveal": false
              },
              "icon": "lucide-folder-closed",
              "title": "Files"
            }
          },
          {
            "id": "ecd081768adcee7e",
            "type": "leaf",
            "state": {
              "type": "search",
              "state": {
                "query": "",
                "matchingCase": false,
                "explainSearch": false,
                "collapseAll": false,
                "extraContext": false,
                "sortOrder": "alphabetical"
              },
              "icon": "lucide-search",
              "title": "Search"
            }
          },
          {
            "id": "f5a97ee82b31111c",
            "type": "leaf",
            "state": {
              "type": "bookmarks",
              "state": {},
              "icon": "lucide-bookmark",
              "title": "Bookmarks"
            }
          }
        ]
      }
    ],
    "direction": "horizontal",
    "width": 300
  },
  "right": {
    "id": "dd7608d44aaaaa18",
    "type": "split",
    "children": [
      {
        "id": "2865180ff1b31092",
        "type": "tabs",
        "children": [
          {
            "id": "da5fb575d055401f",
            "type": "leaf",
            "state": {
              "type": "backlink",
              "state": {
                "file": "🍕 Food Delivery App — Schema Design.md",
                "collapseAll": false,
                "extraContext": false,
                "sortOrder": "alphabetical",
                "showSearch": false,
                "searchQuery": "",
                "backlinkCollapsed": true,
                "unlinkedCollapsed": true
              },
              "icon": "links-coming-in",
              "title": "Backlinks for 🍕 Food Delivery App — Schema Design"
            }
          },
          {
            "id": "f56d15797dced798",
            "type": "leaf",
            "state": {
              "type": "outgoing-link",
              "state": {
                "file": "🍕 Food Delivery App — Schema Design.md",
                "linksCollapsed": false,
                "unlinkedCollapsed": true
              },
              "icon": "links-going-out",
              "title": "Outgoing links from 🍕 Food Delivery App — Schema Design"
            }
          },
          {
            "id": "528fafbc4007b0b1",
            "type": "leaf",
            "state": {
              "type": "tag",
              "state": {
                "sortOrder": "frequency",
                "useHierarchy": true,
                "showSearch": false,
                "searchQuery": ""
              },
              "icon": "lucide-tags",
              "title": "Tags"
            }
          },
          {
            "id": "35ee1df1d470b66a",
            "type": "leaf",
            "state": {
              "type": "all-properties",
              "state": {
                "sortOrder": "frequency",
                "showSearch": false,
                "searchQuery": ""
              },
              "icon": "lucide-archive",
              "title": "All properties"
            }
          },
          {
            "id": "f14935ad97b053b6",
            "type": "leaf",
            "state": {
              "type": "outline",
              "state": {
                "file": "🍕 Food Delivery App — Schema Design.md",
                "followCursor": false,
                "showSearch": false,
                "searchQuery": ""
              },
              "icon": "lucide-list",
              "title": "Outline of 🍕 Food Delivery App — Schema Design"
            }
          }
        ],
        "currentTab": 4
      }
    ],
    "direction": "horizontal",
    "width": 300
  },
  "left-ribbon": {
    "hiddenItems": {
      "switcher:Open quick switcher": false,
      "graph:Open graph view": false,
      "canvas:Create new canvas": false,
      "daily-notes:Open today's daily note": false,
      "templates:Insert template": false,
      "command-palette:Open command palette": false,
      "bases:Create new base": false,
      "obsidian-git:Open Git source control": false,
      "obsidian-excalidraw-plugin:New drawing": false,
      "githobs:Manage a github issue": false,
      "vscode-editor:Create Code File": false
    }
  },
  "active": "76208cb8598e16bd",
  "lastOpenFiles": [
    "DP Questions.md",
    "HLD Study Notes.md",
    "🍕 Food Delivery App — Schema Design.md",
    "Untitled.base",
    "My code file.ts"
  ]
}